marshmallow_tagged_union/__init__.py
marshmallow_tagged_union-0.0.2.dist-info/METADATA
marshmallow_tagged_union-0.0.2.dist-info/WHEEL
marshmallow_tagged_union-0.0.2.dist-info/licenses/LICENSE
marshmallow_tagged_union-0.0.2.dist-info/RECORD
