Metadata-Version: 2.4
Name: marshmallow-tagged-union
Version: 0.0.2
Summary: Provide support for tagged unions in marshmallow schemas
Project-URL: Homepage, https://github.com/The-Gopher/marshmallow-tagged-union
Project-URL: Issues, https://github.com/The-Gopher/marshmallow-tagged-union/issues
Author-email: Mike Franklin <mfranklin@sampleserve.com>
License-File: LICENSE
Classifier: Development Status :: 3 - Alpha
Classifier: Intended Audience :: Developers
Classifier: License :: OSI Approved :: MIT License
Classifier: Operating System :: OS Independent
Classifier: Programming Language :: Python :: 3
Requires-Python: >=3.8
Requires-Dist: marshmallow>=3.0.0
Provides-Extra: dev
Requires-Dist: bandit>=1.7.0; extra == 'dev'
Requires-Dist: black>=23.10.0; extra == 'dev'
Requires-Dist: coverage>=6.0.0; extra == 'dev'
Requires-Dist: isort>=5.12.0; extra == 'dev'
Requires-Dist: pre-commit>=2.0.0; extra == 'dev'
Requires-Dist: pylint>=2.0.0; extra == 'dev'
Requires-Dist: pytest>=7.0.0; extra == 'dev'
